pvl_sdk/__init__.py
pvl_sdk/client.py
pvl_sdk/config.py
pvl_sdk/exceptions.py
pvl_sdk/labs.py
pvl_sdk/models.py
pvl_sdk/nodes.py
pvl_sdk/utils.py
pvl_sdk-0.1.0.dist-info/METADATA
pvl_sdk-0.1.0.dist-info/WHEEL
pvl_sdk-0.1.0.dist-info/RECORD
