Metadata-Version: 2.1
Name: pvl_sdk
Version: 0.1.0
Summary: Python SDK for FastAPI backend
License: MIT
Author: Narasimman Rajendran
Author-email: your-email@example.com
Requires-Python: >=3.8,<4.0
Classifier: License :: OSI Approved :: MIT License
Classifier: Programming Language :: Python :: 3
Classifier: Programming Language :: Python :: 3.8
Classifier: Programming Language :: Python :: 3.9
Classifier: Programming Language :: Python :: 3.10
Classifier: Programming Language :: Python :: 3.11
Classifier: Programming Language :: Python :: 3.12
Classifier: Programming Language :: Python :: 3.13
Requires-Dist: requests (>=2.26,<3.0)
